linko_mcp/__init__.py
linko_mcp/api_client.py
linko_mcp/auth.py
linko_mcp/linko_for_AI.py
linko_mcp/linko_mcp.py
linko_mcp-0.2.2.dist-info/licenses/LICENSE
linko_mcp-0.2.2.dist-info/METADATA
linko_mcp-0.2.2.dist-info/WHEEL
linko_mcp-0.2.2.dist-info/entry_points.txt
linko_mcp-0.2.2.dist-info/top_level.txt
linko_mcp-0.2.2.dist-info/RECORD
