Metadata-Version: 2.4
Name: linko-mcp
Version: 0.2.2
Summary: Linko MCP - Access your Linko study notes and resources through LLMs
Home-page: https://github.com/tianqijiang/linko_mcp
Author: Tianqi
Author-email: tianqijiang.dec@gmail.com
Project-URL: Bug Tracker, https://github.com/tianqijiang/linko_mcp/issues
Project-URL: Documentation, https://github.com/tianqijiang/linko_mcp
Project-URL: Source Code, https://github.com/tianqijiang/linko_mcp
Classifier: Development Status :: 4 - Beta
Classifier: Intended Audience :: Developers
Classifier: Intended Audience :: Science/Research
Classifier: Programming Language :: Python :: 3
Classifier: Programming Language :: Python :: 3.10
Classifier: Programming Language :: Python :: 3.11
Classifier: Programming Language :: Python :: 3.12
Classifier: License :: OSI Approved :: MIT License
Classifier: Operating System :: OS Independent
Classifier: Topic :: Education
Classifier: Topic :: Scientific/Engineering :: Artificial Intelligence
Requires-Python: >=3.10
License-File: LICENSE
Requires-Dist: mcp[cli]>=1.6.0
Requires-Dist: requests>=2.31.0
Requires-Dist: httpx>=0.24.0
Dynamic: author
Dynamic: author-email
Dynamic: classifier
Dynamic: description
Dynamic: description-content-type
Dynamic: home-page
Dynamic: license-file
Dynamic: project-url
Dynamic: requires-dist
Dynamic: requires-python
Dynamic: summary
